{
  "project_name": "tech-lead-tony",
  "planning_started_at": "2025-06-30T20:34:00-05:00",
  "current_phase": "planning_complete",
  "phases": {
    "phase_1_abstraction": {
      "status": "completed",
      "completed_at": "2025-07-01T12:00:00Z",
      "tree_count": 10
    },
    "phase_2_decomposition": {
      "status": "completed",
      "completed_at": "2025-07-01T13:30:00Z",
      "trees_processed": ["1.000", "2.000", "3.000", "4.000", "5.000", "6.000", "7.000", "8.000", "9.000", "10.000"],
      "current_tree": null
    },
    "phase_3_second_pass": {
      "status": "completed",
      "completed_at": "2025-07-01T14:00:00Z",
      "gaps_identified": 52,
      "tasks_added": 52
    }
  },
  "ultrathink_rules": {
    "single_tree_focus": true,
    "complete_before_continue": true,
    "no_premature_optimization": true,
    "no_implementation_planning": true
  },
  "metrics": {
    "total_tasks_planned": 0,
    "atomic_tasks": 0,
    "micro_tasks": 0,
    "planning_time_minutes": 0
  }
}
